piazza_api/__init__.py
piazza_api/exceptions.py
piazza_api/network.py
piazza_api/nonce.py
piazza_api/piazza.py
piazza_api/rpc.py
piazza_api-0.15.0.dist-info/licenses/LICENSE
piazza_api-0.15.0.dist-info/METADATA
piazza_api-0.15.0.dist-info/WHEEL
piazza_api-0.15.0.dist-info/top_level.txt
piazza_api-0.15.0.dist-info/RECORD
